dynamore/__init__.py
dynamore/dynamodb_proxy.py
dynamore/entity.py
dynamore/utils.py
dynamore/validator.py
dynamore-0.1.1.dist-info/WHEEL
dynamore-0.1.1.dist-info/METADATA
dynamore-0.1.1.dist-info/RECORD
