Metadata-Version: 2.1
Name: dynamore
Version: 0.1.1
Summary: Dynamore is extremely simple Python library for managing entities on DynamoDb.
Home-page: https://github.com/villekr/dynamore
License: MIT
Author: Ville Kärkkäinen
Author-email: ville.karkkainen@outlook.com
Requires-Python: >=3.8,<4.0
Classifier: Development Status :: 3 - Alpha
Classifier: License :: OSI Approved :: MIT License
Classifier: Programming Language :: Python :: 3
Classifier: Programming Language :: Python :: 3.6
Classifier: Programming Language :: Python :: 3.7
Classifier: Programming Language :: Python :: 3.8
Requires-Dist: boto3 (==1.12.32)
Requires-Dist: jsonschema (>=3.2.0,<4.0.0)
Requires-Dist: python-dotenv (>=0.14.0,<0.15.0)
Project-URL: Repository, https://github.com/villekr/dynamore
